datacast/__init__.py
datacast/base.py
datacast/caster.py
datacast/env.py
datacast/errors.py
datacast/main.py
datacast-0.3.5.dist-info/LICENSE
datacast-0.3.5.dist-info/METADATA
datacast-0.3.5.dist-info/WHEEL
datacast-0.3.5.dist-info/top_level.txt
datacast-0.3.5.dist-info/RECORD
