Metadata-Version: 2.1
Name: datacast
Version: 0.3.5
Summary: Simple way to cast your data.
Home-page: https://github.com/fatemonk/datacast
Author: Alexander Rulkov
Author-email: fatemonk@gmail.com
License: MIT
Keywords: config,env,data,cast
Platform: UNKNOWN
Classifier: Intended Audience :: Developers
Classifier: Topic :: Software Development :: Build Tools
Classifier: License :: OSI Approved :: MIT License
Classifier: Programming Language :: Python :: 3
Classifier: Programming Language :: Python :: 3.3
Requires-Python: >=3.3
